{
    "0": [
        "green",
        "tree",
        "grass",
        "ball",
        "man"
    ],
    "1": [
        "camera",
        "building",
        "woman",
        "ball",
        "grass"
    ],
    "2": [
        "green",
        "bag",
        "white",
        "ball",
        "tree"
    ],
    "3": [
        "dog",
        "man",
        "ball",
        "bag",
        "grass"
    ],
    "4": [
        "ball",
        "male",
        "glove",
        "bat",
        "female"
    ],
    "5": [
        "ball",
        "bag",
        "male",
        "bat",
        "picture"
    ],
    "6": [
        "green",
        "white",
        "people",
        "ball",
        "hole"
    ],
    "7": [
        "ball",
        "people",
        "kite",
        "grass",
        "field"
    ],
    "8": [
        "grass",
        "tree",
        "person",
        "motorcycle",
        "helmet"
    ],
    "9": [
        "ball",
        "green",
        "man",
        "stick",
        "bat"
    ],
    "10": [
        "ball",
        "person",
        "green",
        "rack",
        "yellow"
    ],
    "11": [
        "ball",
        "can",
        "male",
        "person",
        "man"
    ],
    "12": [
        "people",
        "bat",
        "dog",
        "ball",
        "man"
    ],
    "13": [
        "ball",
        "bat",
        "person",
        "green",
        "field"
    ],
    "14": [
        "ball",
        "man",
        "green",
        "pole",
        "grass"
    ],
    "15": [
        "male",
        "dog",
        "stick",
        "grass",
        "baseball"
    ],
    "16": [
        "ball",
        "person",
        "grass",
        "bag",
        "green"
    ],
    "17": [
        "people",
        "tree",
        "grass",
        "bench",
        "rack"
    ],
    "18": [
        "green",
        "water",
        "white",
        "ball",
        "male"
    ],
    "19": [
        "camera",
        "man",
        "building",
        "tree",
        "grass"
    ],
    "20": [
        "ball",
        "green",
        "tree",
        "man",
        "grass"
    ],
    "21": [
        "ball",
        "green",
        "bat",
        "stick",
        "black"
    ],
    "22": [
        "green",
        "ball",
        "white",
        "fence",
        "people"
    ],
    "23": [
        "ball",
        "green",
        "man",
        "dog",
        "people"
    ],
    "24": [
        "man",
        "dog",
        "grass",
        "woman",
        "tree"
    ],
    "25": [
        "bag",
        "man",
        "grass",
        "ball",
        "fence"
    ],
    "26": [
        "ball",
        "green",
        "bat",
        "man",
        "trees"
    ],
    "27": [
        "ball",
        "people",
        "bat",
        "fence",
        "grass"
    ],
    "28": [
        "green",
        "white",
        "red",
        "tree",
        "pole"
    ],
    "29": [
        "ball",
        "glove",
        "male",
        "bat",
        "man"
    ],
    "30": [
        "ball",
        "male",
        "female",
        "tree",
        "bat"
    ],
    "31": [
        "green",
        "ball",
        "man",
        "black",
        "field"
    ],
    "32": [
        "ball",
        "people",
        "tree",
        "grass",
        "dog"
    ],
    "33": [
        "people",
        "fence",
        "tree",
        "grass",
        "dog"
    ],
    "34": [
        "green",
        "ball",
        "white",
        "male",
        "stick"
    ],
    "35": [
        "ball",
        "rack",
        "female",
        "tennis",
        "male"
    ],
    "36": [
        "people",
        "grass",
        "fence",
        "tree",
        "field"
    ],
    "37": [
        "man",
        "building",
        "grass",
        "green",
        "truck"
    ],
    "38": [
        "ball",
        "man",
        "camera",
        "grass",
        "green"
    ],
    "39": [
        "green",
        "trees",
        "man",
        "dog",
        "ball"
    ],
    "40": [
        "white",
        "green",
        "tree",
        "people",
        "sign"
    ],
    "41": [
        "ball",
        "green",
        "man",
        "grass",
        "bat"
    ],
    "42": [
        "green",
        "white",
        "ball",
        "bushes",
        "tree"
    ],
    "43": [
        "green",
        "ball",
        "woman",
        "grass",
        "tree"
    ],
    "44": [
        "ball",
        "woman",
        "tree",
        "bat",
        "grass"
    ],
    "45": [
        "ball",
        "tree",
        "grass",
        "green",
        "woman"
    ],
    "46": [
        "ball",
        "green",
        "man",
        "bat",
        "tree"
    ],
    "47": [
        "ball",
        "tv",
        "man",
        "glove",
        "green"
    ],
    "48": [
        "green",
        "ball",
        "white",
        "black",
        "woman"
    ],
    "49": [
        "ball",
        "bat",
        "field",
        "people",
        "man"
    ],
    "50": [
        "people",
        "umbrella",
        "dog",
        "grass",
        "bag"
    ],
    "51": [
        "green",
        "white",
        "tree",
        "black",
        "pole"
    ],
    "52": [
        "people",
        "fence",
        "grass",
        "bat",
        "sign"
    ],
    "53": [
        "white",
        "green",
        "black",
        "woman",
        "people"
    ],
    "54": [
        "man",
        "building",
        "grass",
        "tree",
        "truck"
    ],
    "55": [
        "ball",
        "male",
        "bat",
        "glove",
        "baseball"
    ],
    "56": [
        "ball",
        "bag",
        "man",
        "bat",
        "dog"
    ],
    "57": [
        "ball",
        "green",
        "male",
        "dog",
        "people"
    ],
    "58": [
        "ball",
        "bag",
        "person",
        "grass",
        "green"
    ],
    "59": [
        "fence",
        "grass",
        "male",
        "ball",
        "bag"
    ],
    "60": [
        "sign",
        "people",
        "motorcycle",
        "green",
        "white"
    ],
    "61": [
        "ball",
        "green",
        "black",
        "white",
        "male"
    ],
    "62": [
        "green",
        "sign",
        "tree",
        "white",
        "ball"
    ],
    "63": [
        "fence",
        "people",
        "grass",
        "tree",
        "field"
    ],
    "64": [
        "ball",
        "male",
        "female",
        "green",
        "glove"
    ],
    "65": [
        "green",
        "ball",
        "tree",
        "trees",
        "pole"
    ],
    "66": [
        "green",
        "white",
        "water",
        "ball",
        "tree"
    ],
    "67": [
        "bag",
        "people",
        "sign",
        "grass",
        "tent"
    ],
    "68": [
        "green",
        "pond",
        "grass",
        "hill",
        "person"
    ],
    "69": [
        "ball",
        "man",
        "green",
        "bat",
        "sign"
    ],
    "70": [
        "bench",
        "phone",
        "bridge",
        "cell",
        "fence"
    ],
    "71": [
        "bench",
        "fence",
        "building",
        "male",
        "phone"
    ],
    "72": [
        "bar",
        "rope",
        "person",
        "gym",
        "bag"
    ],
    "73": [
        "man",
        "monitor",
        "desk",
        "television",
        "shirt"
    ],
    "74": [
        "tree",
        "fence",
        "pole",
        "chair",
        "grass"
    ],
    "75": [
        "man",
        "building",
        "pole",
        "wall",
        "rope"
    ],
    "76": [
        "man",
        "window",
        "table",
        "chair",
        "couch"
    ],
    "77": [
        "tree",
        "pole",
        "shirt",
        "male",
        "person"
    ],
    "78": [
        "stairs",
        "man",
        "wall",
        "woman",
        "door"
    ],
    "79": [
        "fence",
        "tree",
        "building",
        "person",
        "pole"
    ],
    "80": [
        "tree",
        "fence",
        "bench",
        "stairs",
        "person"
    ],
    "81": [
        "male",
        "fence",
        "street",
        "building",
        "shirt"
    ],
    "82": [
        "monitor",
        "man",
        "desk",
        "television",
        "shirt"
    ],
    "83": [
        "man",
        "pole",
        "umbrella",
        "tree",
        "bars"
    ],
    "84": [
        "window",
        "chair",
        "table",
        "mirror",
        "person"
    ],
    "85": [
        "shirt",
        "male",
        "chair",
        "towel",
        "female"
    ],
    "86": [
        "male",
        "fence",
        "street",
        "man",
        "shirt"
    ],
    "87": [
        "woman",
        "cabinet",
        "refrigerator",
        "sink",
        "door"
    ],
    "88": [
        "male",
        "pole",
        "tree",
        "shirt",
        "umbrella"
    ],
    "89": [
        "refrigerator",
        "dog",
        "door",
        "woman",
        "cabinet"
    ],
    "90": [
        "monitor",
        "man",
        "desk",
        "phone",
        "rope"
    ],
    "91": [
        "window",
        "man",
        "table",
        "couch",
        "bench"
    ],
    "92": [
        "bar",
        "gym",
        "woman",
        "bag",
        "person"
    ],
    "93": [
        "male",
        "pole",
        "tree",
        "shirt",
        "female"
    ],
    "94": [
        "rack",
        "man",
        "towel",
        "chair",
        "wall"
    ],
    "95": [
        "fence",
        "tree",
        "person",
        "stairs",
        "bench"
    ],
    "96": [
        "male",
        "fence",
        "street",
        "building",
        "pole"
    ],
    "97": [
        "fence",
        "bench",
        "male",
        "building",
        "bridge"
    ],
    "98": [
        "television",
        "man",
        "desk",
        "monitor",
        "clock"
    ],
    "99": [
        "tree",
        "pole",
        "male",
        "shirt",
        "female"
    ],
    "100": [
        "pole",
        "people",
        "rope",
        "woman",
        "building"
    ],
    "101": [
        "gym",
        "bar",
        "bag",
        "woman",
        "rack"
    ],
    "102": [
        "mirror",
        "window",
        "woman",
        "wall",
        "shirt"
    ],
    "103": [
        "bar",
        "man",
        "towel",
        "gym",
        "rope"
    ],
    "104": [
        "male",
        "fence",
        "ball",
        "field",
        "building"
    ],
    "105": [
        "mirror",
        "window",
        "woman",
        "toilet",
        "sink"
    ],
    "106": [
        "rack",
        "chair",
        "man",
        "wall",
        "towel"
    ],
    "107": [
        "man",
        "window",
        "table",
        "chair",
        "couch"
    ],
    "108": [
        "fence",
        "male",
        "ball",
        "female",
        "field"
    ],
    "109": [
        "fence",
        "tree",
        "person",
        "bench",
        "board"
    ],
    "110": [
        "window",
        "wall",
        "male",
        "female",
        "rope"
    ],
    "111": [
        "people",
        "tent",
        "microphone",
        "stage",
        "sign"
    ],
    "112": [
        "shirt",
        "chair",
        "man",
        "male",
        "bar"
    ],
    "113": [
        "window",
        "table",
        "man",
        "chair",
        "dog"
    ],
    "114": [
        "pole",
        "people",
        "tree",
        "umbrella",
        "building"
    ],
    "115": [
        "sign",
        "people",
        "stage",
        "tent",
        "microphone"
    ],
    "116": [
        "bar",
        "shirt",
        "man",
        "chair",
        "towel"
    ],
    "117": [
        "man",
        "wall",
        "mirror",
        "woman",
        "rope"
    ],
    "118": [
        "pole",
        "people",
        "tree",
        "bus",
        "umbrella"
    ],
    "119": [
        "fence",
        "male",
        "field",
        "ball",
        "chain"
    ],
    "120": [
        "dog",
        "door",
        "refrigerator",
        "window",
        "woman"
    ],
    "121": [
        "window",
        "wall",
        "tree",
        "man",
        "picture"
    ],
    "122": [
        "man",
        "wall",
        "mirror",
        "rope",
        "building"
    ],
    "123": [
        "wall",
        "stairs",
        "male",
        "man",
        "female"
    ],
    "124": [
        "rope",
        "person",
        "board",
        "pole",
        "chair"
    ],
    "125": [
        "window",
        "man",
        "table",
        "bat",
        "cup"
    ],
    "126": [
        "people",
        "tent",
        "microphone",
        "stage",
        "sign"
    ],
    "127": [
        "bar",
        "bag",
        "gym",
        "woman",
        "female"
    ],
    "128": [
        "rack",
        "man",
        "gym",
        "board",
        "wall"
    ],
    "129": [
        "mirror",
        "window",
        "woman",
        "sink",
        "female"
    ],
    "130": [
        "pole",
        "tree",
        "umbrella",
        "male",
        "sign"
    ],
    "131": [
        "bar",
        "gym",
        "man",
        "towel",
        "person"
    ],
    "132": [
        "people",
        "pole",
        "woman",
        "building",
        "rope"
    ],
    "133": [
        "man",
        "monitor",
        "desk",
        "shirt",
        "clock"
    ],
    "134": [
        "television",
        "man",
        "desk",
        "monitor",
        "tv"
    ],
    "135": [
        "window",
        "wall",
        "male",
        "female",
        "tree"
    ],
    "136": [
        "tree",
        "pole",
        "ball",
        "male",
        "umbrella"
    ],
    "137": [
        "ball",
        "male",
        "red",
        "bat",
        "field"
    ],
    "138": [
        "microphone",
        "male",
        "female",
        "man",
        "table"
    ],
    "139": [
        "wall",
        "male",
        "female",
        "rack",
        "person"
    ],
    "140": [
        "male",
        "female",
        "tie",
        "window",
        "shirt"
    ],
    "141": [
        "gun",
        "man",
        "woman",
        "person",
        "camera"
    ],
    "142": [
        "man",
        "people",
        "woman",
        "picture",
        "ball"
    ],
    "143": [
        "man",
        "woman",
        "dog",
        "people",
        "building"
    ],
    "144": [
        "male",
        "ball",
        "rope",
        "rack",
        "female"
    ],
    "145": [
        "ball",
        "rack",
        "clock",
        "man",
        "people"
    ],
    "146": [
        "fence",
        "bat",
        "people",
        "man",
        "ball"
    ],
    "147": [
        "camera",
        "female",
        "male",
        "boy",
        "people"
    ],
    "148": [
        "ball",
        "rack",
        "male",
        "people",
        "bat"
    ],
    "149": [
        "wall",
        "male",
        "person",
        "rope",
        "female"
    ],
    "150": [
        "field",
        "tree",
        "people",
        "sheep",
        "dog"
    ],
    "151": [
        "man",
        "stairs",
        "picture",
        "male",
        "female"
    ],
    "152": [
        "male",
        "ball",
        "female",
        "wall",
        "rack"
    ],
    "153": [
        "male",
        "stairs",
        "window",
        "female",
        "man"
    ],
    "154": [
        "ball",
        "man",
        "male",
        "female",
        "rack"
    ],
    "155": [
        "man",
        "male",
        "woman",
        "pan",
        "female"
    ],
    "156": [
        "laptop",
        "microphone",
        "camera",
        "man",
        "male"
    ],
    "157": [
        "man",
        "woman",
        "male",
        "female",
        "window"
    ],
    "158": [
        "male",
        "table",
        "couch",
        "lamp",
        "female"
    ],
    "159": [
        "male",
        "female",
        "ball",
        "wall",
        "rack"
    ],
    "160": [
        "picture",
        "person",
        "man",
        "female",
        "male"
    ],
    "161": [
        "man",
        "woman",
        "wall",
        "rack",
        "bicycle"
    ],
    "162": [
        "rack",
        "male",
        "ball",
        "female",
        "person"
    ],
    "163": [
        "female",
        "male",
        "person",
        "ball",
        "rope"
    ],
    "164": [
        "man",
        "woman",
        "horse",
        "building",
        "tree"
    ],
    "165": [
        "people",
        "street",
        "tree",
        "man",
        "horse"
    ],
    "166": [
        "table",
        "man",
        "chair",
        "male",
        "woman"
    ],
    "167": [
        "male",
        "female",
        "ball",
        "camera",
        "sign"
    ],
    "168": [
        "male",
        "female",
        "ball",
        "belt",
        "wall"
    ],
    "169": [
        "ball",
        "net",
        "male",
        "rack",
        "female"
    ],
    "170": [
        "ball",
        "male",
        "rack",
        "female",
        "net"
    ],
    "171": [
        "person",
        "ball",
        "male",
        "wall",
        "bat"
    ],
    "172": [
        "rack",
        "ball",
        "male",
        "net",
        "female"
    ],
    "173": [
        "fence",
        "man",
        "motorcycle",
        "horse",
        "field"
    ],
    "174": [
        "man",
        "ball",
        "male",
        "female",
        "belt"
    ],
    "175": [
        "man",
        "rack",
        "light",
        "camera",
        "wall"
    ],
    "176": [
        "people",
        "skate",
        "street",
        "wall",
        "tree"
    ],
    "177": [
        "male",
        "female",
        "person",
        "ball",
        "people"
    ],
    "178": [
        "man",
        "ball",
        "rack",
        "table",
        "bat"
    ],
    "179": [
        "male",
        "microphone",
        "female",
        "man",
        "guitar"
    ],
    "180": [
        "person",
        "door",
        "window",
        "man",
        "picture"
    ],
    "181": [
        "camera",
        "female",
        "male",
        "person",
        "microphone"
    ],
    "182": [
        "male",
        "female",
        "rack",
        "wall",
        "person"
    ],
    "183": [
        "man",
        "woman",
        "board",
        "wall",
        "people"
    ],
    "184": [
        "mirror",
        "wall",
        "male",
        "female",
        "clock"
    ],
    "185": [
        "tie",
        "man",
        "window",
        "shirt",
        "door"
    ],
    "186": [
        "ball",
        "male",
        "female",
        "rack",
        "wall"
    ],
    "187": [
        "male",
        "female",
        "rack",
        "ball",
        "hoop"
    ],
    "188": [
        "man",
        "woman",
        "rope",
        "gun",
        "camera"
    ],
    "189": [
        "wall",
        "male",
        "female",
        "ball",
        "picture"
    ],
    "190": [
        "fence",
        "man",
        "people",
        "catcher",
        "horse"
    ],
    "191": [
        "male",
        "window",
        "female",
        "person",
        "chair"
    ],
    "192": [
        "wall",
        "doll",
        "phone",
        "girl",
        "wire"
    ],
    "193": [
        "trees",
        "tree",
        "kite",
        "person",
        "shirt"
    ],
    "194": [
        "rope",
        "wall",
        "person",
        "people",
        "climbing"
    ],
    "195": [
        "fence",
        "person",
        "roof",
        "building",
        "tree"
    ],
    "196": [
        "wall",
        "building",
        "person",
        "man",
        "rope"
    ],
    "197": [
        "building",
        "person",
        "tree",
        "dirt",
        "blanket"
    ],
    "198": [
        "bucket",
        "man",
        "pole",
        "rope",
        "helmet"
    ],
    "199": [
        "wall",
        "board",
        "person",
        "shoes",
        "sign"
    ],
    "200": [
        "person",
        "wall",
        "board",
        "sign",
        "rope"
    ],
    "201": [
        "sign",
        "wall",
        "window",
        "man",
        "people"
    ],
    "202": [
        "wall",
        "phone",
        "climbing",
        "window",
        "shower"
    ],
    "203": [
        "man",
        "bucket",
        "pole",
        "rope",
        "helmet"
    ],
    "204": [
        "fence",
        "building",
        "board",
        "man",
        "person"
    ],
    "205": [
        "wall",
        "rope",
        "man",
        "board",
        "climbing"
    ],
    "206": [
        "rock",
        "rope",
        "tree",
        "man",
        "stick"
    ],
    "207": [
        "rope",
        "wall",
        "person",
        "stairs",
        "ball"
    ],
    "208": [
        "ball",
        "wall",
        "building",
        "male",
        "yellow"
    ],
    "209": [
        "rope",
        "ceiling",
        "window",
        "man",
        "person"
    ],
    "210": [
        "picture",
        "bird",
        "rock",
        "man",
        "bear"
    ],
    "211": [
        "bird",
        "rock",
        "plant",
        "tree",
        "male"
    ],
    "212": [
        "wall",
        "man",
        "rope",
        "climbing",
        "boy"
    ],
    "213": [
        "rope",
        "rock",
        "person",
        "wall",
        "tree"
    ],
    "214": [
        "wall",
        "man",
        "rope",
        "box",
        "balloons"
    ],
    "215": [
        "bucket",
        "pole",
        "man",
        "banana",
        "sign"
    ],
    "216": [
        "wall",
        "rope",
        "door",
        "chair",
        "child"
    ],
    "217": [
        "tree",
        "rock",
        "wall",
        "bird",
        "stick"
    ],
    "218": [
        "rope",
        "wall",
        "person",
        "man",
        "bottle"
    ],
    "219": [
        "tree",
        "man",
        "bird",
        "rope",
        "chicken"
    ],
    "220": [
        "tree",
        "rock",
        "rope",
        "male",
        "lizard"
    ],
    "221": [
        "rock",
        "tree",
        "lizard",
        "stick",
        "bear"
    ],
    "222": [
        "ball",
        "picture",
        "male",
        "bat",
        "man"
    ],
    "223": [
        "motorcycle",
        "sign",
        "car",
        "man",
        "street"
    ],
    "224": [
        "building",
        "pole",
        "person",
        "tree",
        "fence"
    ],
    "225": [
        "male",
        "rock",
        "female",
        "wall",
        "tree"
    ],
    "226": [
        "rope",
        "person",
        "tree",
        "wall",
        "monkey"
    ],
    "227": [
        "rock",
        "stick",
        "man",
        "tree",
        "bear"
    ],
    "228": [
        "ball",
        "male",
        "female",
        "stick",
        "tree"
    ],
    "229": [
        "roof",
        "tree",
        "person",
        "fence",
        "building"
    ],
    "230": [
        "fence",
        "building",
        "man",
        "backpack",
        "male"
    ],
    "231": [
        "wall",
        "building",
        "backpack",
        "man",
        "climbing"
    ],
    "232": [
        "rope",
        "climbing",
        "wall",
        "person",
        "man"
    ],
    "233": [
        "wall",
        "stick",
        "person",
        "ball",
        "man"
    ],
    "234": [
        "fence",
        "building",
        "man",
        "pole",
        "phone"
    ],
    "235": [
        "building",
        "sign",
        "person",
        "tree",
        "bench"
    ],
    "236": [
        "tree",
        "building",
        "people",
        "pole",
        "sign"
    ],
    "237": [
        "rope",
        "tree",
        "man",
        "wall",
        "climbing"
    ],
    "238": [
        "wall",
        "climbing",
        "backpack",
        "man",
        "rope"
    ],
    "239": [
        "ball",
        "man",
        "bat",
        "stick",
        "rope"
    ],
    "240": [
        "door",
        "bottle",
        "wall",
        "girl",
        "lock"
    ],
    "241": [
        "wall",
        "person",
        "phone",
        "man",
        "board"
    ],
    "242": [
        "fence",
        "rope",
        "tree",
        "person",
        "trees"
    ],
    "243": [
        "man",
        "rock",
        "bear",
        "tree",
        "wall"
    ],
    "244": [
        "bird",
        "dog",
        "tree",
        "man",
        "rock"
    ],
    "245": [
        "wall",
        "window",
        "sign",
        "person",
        "building"
    ],
    "246": [
        "cross",
        "sky",
        "picture",
        "plane",
        "bird"
    ],
    "247": [
        "roof",
        "person",
        "tree",
        "building",
        "grass"
    ],
    "248": [
        "rope",
        "rock",
        "stick",
        "man",
        "boy"
    ],
    "249": [
        "rock",
        "bridge",
        "man",
        "mountain",
        "people"
    ],
    "250": [
        "wall",
        "rope",
        "board",
        "man",
        "sign"
    ],
    "251": [
        "wall",
        "person",
        "window",
        "male",
        "ceiling"
    ],
    "252": [
        "rope",
        "person",
        "wall",
        "man",
        "dog"
    ],
    "253": [
        "male",
        "female",
        "lamp",
        "curtain",
        "phone"
    ],
    "254": [
        "male",
        "female",
        "man",
        "woman",
        "people"
    ],
    "255": [
        "man",
        "male",
        "mirror",
        "window",
        "female"
    ],
    "256": [
        "wall",
        "male",
        "picture",
        "gloves",
        "ball"
    ],
    "257": [
        "wall",
        "balloons",
        "black",
        "bag",
        "picture"
    ],
    "258": [
        "mirror",
        "chair",
        "table",
        "people",
        "bed"
    ],
    "259": [
        "door",
        "male",
        "female",
        "man",
        "mirror"
    ],
    "260": [
        "bear",
        "man",
        "gun",
        "woman",
        "picture"
    ],
    "261": [
        "couch",
        "table",
        "people",
        "window",
        "wall"
    ],
    "262": [
        "male",
        "door",
        "female",
        "man",
        "window"
    ],
    "263": [
        "man",
        "male",
        "chair",
        "rack",
        "female"
    ],
    "264": [
        "male",
        "female",
        "mirror",
        "picture",
        "man"
    ],
    "265": [
        "dog",
        "chair",
        "couch",
        "table",
        "lamp"
    ],
    "266": [
        "male",
        "wall",
        "female",
        "black",
        "boxing"
    ],
    "267": [
        "male",
        "ball",
        "black",
        "boxing",
        "ring"
    ],
    "268": [
        "male",
        "female",
        "man",
        "mirror",
        "table"
    ],
    "269": [
        "couch",
        "chair",
        "table",
        "person",
        "dog"
    ],
    "270": [
        "male",
        "couch",
        "female",
        "wall",
        "man"
    ],
    "271": [
        "monkey",
        "female",
        "male",
        "lion",
        "rock"
    ],
    "272": [
        "road",
        "car",
        "field",
        "boy",
        "female"
    ],
    "273": [
        "man",
        "tree",
        "woman",
        "hill",
        "boy"
    ],
    "274": [
        "cat",
        "fence",
        "male",
        "woman",
        "man"
    ],
    "275": [
        "male",
        "female",
        "man",
        "woman",
        "people"
    ],
    "276": [
        "wall",
        "man",
        "table",
        "television",
        "chair"
    ],
    "277": [
        "building",
        "fence",
        "woman",
        "railing",
        "man"
    ],
    "278": [
        "couch",
        "person",
        "shirt",
        "dog",
        "bag"
    ],
    "279": [
        "male",
        "boxing",
        "ring",
        "wall",
        "bag"
    ],
    "280": [
        "man",
        "stairs",
        "woman",
        "dog",
        "suitcase"
    ],
    "281": [
        "male",
        "door",
        "man",
        "woman",
        "window"
    ],
    "282": [
        "lamp",
        "male",
        "beard",
        "shirt",
        "jacket"
    ],
    "283": [
        "wall",
        "male",
        "picture",
        "man",
        "boxing"
    ],
    "284": [
        "man",
        "picture",
        "woman",
        "male",
        "door"
    ],
    "285": [
        "male",
        "ring",
        "female",
        "man",
        "boxing"
    ],
    "286": [
        "gun",
        "soldier",
        "man",
        "person",
        "rope"
    ],
    "287": [
        "shirt",
        "man",
        "woman",
        "bear",
        "tie"
    ],
    "288": [
        "male",
        "mirror",
        "female",
        "television",
        "stove"
    ],
    "289": [
        "male",
        "female",
        "mirror",
        "door",
        "sink"
    ],
    "290": [
        "building",
        "tree",
        "grass",
        "male",
        "horse"
    ],
    "291": [
        "man",
        "male",
        "train",
        "woman",
        "door"
    ],
    "292": [
        "picture",
        "wall",
        "man",
        "ball",
        "male"
    ],
    "293": [
        "plant",
        "window",
        "laptop",
        "woman",
        "person"
    ],
    "294": [
        "beer",
        "man",
        "male",
        "bottle",
        "refrigerator"
    ],
    "295": [
        "male",
        "boxing",
        "picture",
        "balloons",
        "wall"
    ],
    "296": [
        "man",
        "people",
        "television",
        "microphone",
        "gun"
    ],
    "297": [
        "door",
        "window",
        "plant",
        "man",
        "person"
    ],
    "298": [
        "male",
        "train",
        "man",
        "window",
        "seats"
    ],
    "299": [
        "stove",
        "man",
        "beer",
        "male",
        "camera"
    ],
    "300": [
        "male",
        "black",
        "boxing",
        "wall",
        "ball"
    ],
    "301": [
        "male",
        "female",
        "wii",
        "light",
        "controller"
    ],
    "302": [
        "kite",
        "male",
        "towel",
        "female",
        "tent"
    ],
    "303": [
        "grass",
        "car",
        "road",
        "people",
        "male"
    ],
    "304": [
        "person",
        "chair",
        "table",
        "rack",
        "belt"
    ],
    "305": [
        "window",
        "wall",
        "man",
        "person",
        "couch"
    ],
    "306": [
        "wall",
        "man",
        "boxing",
        "picture",
        "bag"
    ],
    "307": [
        "man",
        "tie",
        "woman",
        "television",
        "shirt"
    ],
    "308": [
        "male",
        "female",
        "picture",
        "man",
        "building"
    ],
    "309": [
        "bag",
        "male",
        "wall",
        "female",
        "ball"
    ],
    "310": [
        "fish",
        "stick",
        "female",
        "woman",
        "male"
    ],
    "311": [
        "mirror",
        "male",
        "suit",
        "tie",
        "man"
    ],
    "312": [
        "man",
        "woman",
        "people",
        "picture",
        "wii"
    ],
    "313": [
        "male",
        "gun",
        "man",
        "female",
        "mirror"
    ],
    "314": [
        "picture",
        "wall",
        "male",
        "ball",
        "man"
    ],
    "315": [
        "bear",
        "man",
        "cat",
        "couch",
        "blanket"
    ],
    "316": [
        "male",
        "wall",
        "boxing",
        "man",
        "guitar"
    ],
    "317": [
        "wall",
        "male",
        "black",
        "boxing",
        "man"
    ],
    "318": [
        "male",
        "man",
        "female",
        "woman",
        "door"
    ],
    "319": [
        "male",
        "female",
        "camera",
        "table",
        "picture"
    ],
    "320": [
        "table",
        "man",
        "people",
        "male",
        "woman"
    ],
    "321": [
        "male",
        "female",
        "hat",
        "mirror",
        "man"
    ],
    "322": [
        "cat",
        "male",
        "female",
        "bear",
        "man"
    ],
    "323": [
        "ball",
        "picture",
        "people",
        "man",
        "horse"
    ],
    "324": [
        "board",
        "people",
        "camera",
        "man",
        "ball"
    ],
    "325": [
        "ball",
        "soccer",
        "man",
        "men",
        "woman"
    ],
    "326": [
        "ball",
        "field",
        "male",
        "light",
        "on"
    ],
    "327": [
        "ball",
        "field",
        "people",
        "male",
        "soccer"
    ],
    "328": [
        "ball",
        "male",
        "female",
        "field",
        "soccer"
    ],
    "329": [
        "ball",
        "glove",
        "men",
        "base",
        "bat"
    ],
    "330": [
        "man",
        "wall",
        "car",
        "woman",
        "bushes"
    ],
    "331": [
        "ball",
        "children",
        "gym",
        "picture",
        "hoop"
    ],
    "332": [
        "ball",
        "children",
        "stick",
        "rope",
        "man"
    ],
    "333": [
        "ball",
        "male",
        "player",
        "field",
        "soccer"
    ],
    "334": [
        "ball",
        "wall",
        "person",
        "people",
        "building"
    ],
    "335": [
        "ball",
        "field",
        "man",
        "car",
        "tree"
    ],
    "336": [
        "ball",
        "field",
        "net",
        "person",
        "male"
    ],
    "337": [
        "ball",
        "male",
        "chair",
        "field",
        "bat"
    ],
    "338": [
        "wall",
        "picture",
        "female",
        "male",
        "clock"
    ],
    "339": [
        "ball",
        "male",
        "man",
        "shirt",
        "fence"
    ],
    "340": [
        "ball",
        "sign",
        "field",
        "man",
        "lights"
    ],
    "341": [
        "car",
        "clock",
        "male",
        "person",
        "wall"
    ],
    "342": [
        "male",
        "man",
        "dog",
        "woman",
        "building"
    ],
    "343": [
        "ball",
        "men",
        "goal",
        "soccer",
        "net"
    ],
    "344": [
        "male",
        "female",
        "picture",
        "wall",
        "ball"
    ],
    "345": [
        "ball",
        "field",
        "soccer",
        "man",
        "white"
    ],
    "346": [
        "ball",
        "people",
        "rack",
        "suitcase",
        "male"
    ],
    "347": [
        "grass",
        "fence",
        "column",
        "window",
        "shoes"
    ],
    "348": [
        "street",
        "wall",
        "people",
        "fence",
        "umbrella"
    ],
    "349": [
        "ball",
        "ring",
        "people",
        "rack",
        "chair"
    ],
    "350": [
        "female",
        "ball",
        "shirt",
        "monitor",
        "wall"
    ],
    "351": [
        "male",
        "television",
        "female",
        "window",
        "man"
    ],
    "352": [
        "ball",
        "net",
        "shirt",
        "male",
        "grass"
    ],
    "353": [
        "ball",
        "male",
        "field",
        "net",
        "person"
    ],
    "354": [
        "ball",
        "man",
        "field",
        "net",
        "soccer"
    ],
    "355": [
        "horse",
        "fire",
        "dog",
        "statue",
        "man"
    ],
    "356": [
        "ball",
        "net",
        "man",
        "people",
        "dog"
    ],
    "357": [
        "television",
        "statue",
        "picture",
        "ball",
        "male"
    ],
    "358": [
        "man",
        "ball",
        "woman",
        "field",
        "male"
    ],
    "359": [
        "ball",
        "field",
        "people",
        "net",
        "bat"
    ],
    "360": [
        "ball",
        "court",
        "children",
        "rack",
        "male"
    ],
    "361": [
        "ball",
        "wall",
        "sidewalk",
        "people",
        "person"
    ],
    "362": [
        "male",
        "female",
        "board",
        "shirt",
        "tv"
    ],
    "363": [
        "male",
        "female",
        "picture",
        "camera",
        "person"
    ],
    "364": [
        "ball",
        "net",
        "soccer",
        "people",
        "field"
    ],
    "365": [
        "ball",
        "male",
        "glove",
        "field",
        "player"
    ],
    "366": [
        "horse",
        "man",
        "cat",
        "black",
        "people"
    ],
    "367": [
        "ball",
        "male",
        "men",
        "man",
        "bat"
    ],
    "368": [
        "ball",
        "soccer",
        "man",
        "male",
        "people"
    ],
    "369": [
        "man",
        "tree",
        "building",
        "dog",
        "fence"
    ],
    "370": [
        "ball",
        "people",
        "rack",
        "gym",
        "children"
    ],
    "371": [
        "people",
        "tree",
        "building",
        "fence",
        "street"
    ],
    "372": [
        "fence",
        "person",
        "grass",
        "ball",
        "chair"
    ],
    "373": [
        "male",
        "female",
        "people",
        "truck",
        "car"
    ],
    "374": [
        "bat",
        "shirt",
        "ball",
        "letter",
        "red"
    ]
}